Workbook

Sheet BOM
A1: FoosPGA - Bill of Materials
A2: Last updated 2026-09-14
A4: Item | B4: Category | C4: Subsystem | D4: Description | E4: Manufacturer | F4: Mfr Part Number | G4: Supplier | H4: Supplier Part Number | I4: Qty | J4: Unit Price | K4: Extended | L4: Tariff | M4: Line Total | N4: Order Ref | O4: Order Date | P4: Status | Q4: Notes
A5: 1 | B5: SoC FPGA | C5: Control & Processing | D5: Kria KV260 Vision AI Starter Kit (K26 SOM + vision carrier) | E5: AMD Xilinx | F5: SK-KV260-G | G5: DigiKey | H5: 122-SK-KV260-G-ND | I5: 1 | J5: 283.86 | K5: =I5*J5 -> 283.86 | L5: 22.71 | M5: =K5+L5 -> 306.57 | N5: DigiKey PO 101582370 | O5: 2026-09-12 | P5: Ordered | Q5: Main compute platform. Non-cancellable / non-returnable (NCNR) accepted at checkout.
A6: 2 | B6: Power | C6: Control & Processing | D6: AC/DC wall mount adapter, 12 V, 36 W | E6: Bel Power Solutions | F6: SMI36-12-V-P6 | G6: DigiKey | H6: 179-SMI36-12-V-P6-ND | I6: 1 | J6: 37.78 | K6: =I6*J6 -> 37.78 | L6: 7.56 | M6: =K6+L6 -> 45.34 | N6: DigiKey PO 101582370 | O6: 2026-09-12 | P6: Ordered | Q6: Power supply for the KV260 (12 V / 3 A).
A7: TOTAL (parts + tariff) | I7: =SUM(I5:I6) -> 2 | K7: =SUM(K5:K6) -> 321.64 | L7: =SUM(L5:L6) -> 30.27 | M7: =SUM(M5:M6) -> 351.91
A9: How to use this sheet
A10: - Add each new part as a row directly ABOVE the TOTAL row so the SUM formulas expand automatically.
A11: - Fill in the blue cells only. Extended (col K) and Line Total (col M) are formulas - do not overwrite them.
A12: - Category (col B) drives the rollup on the Cost tab. Reuse the exact category names listed there, or add the new one to the Cost tab list.

Sheet Cost
B1: Project Cost Summary
B3: Cost by Category | C3: Parts + Tariff | D3: % of Parts | E3: Notes
B4: Compute / FPGA | C4: 306.57 | D4: =IF($C$14=0,0,C4/$C$14) -> 0.87116024 | E4: KV260 board, SOM, future FPGA hardware
B5: Camera / Vision | C5: =SUMIFS(BOM!$M$5:$M$6,BOM!$B$5:$B$6,$B5) -> 0 | D5: =IF($C$14=0,0,C5/$C$14) -> 0 | E5: Camera, lens, lighting, mounts
B6: Motors & Drivers | C6: =SUMIFS(BOM!$M$5:$M$6,BOM!$B$5:$B$6,$B6) -> 0 | D6: =IF($C$14=0,0,C6/$C$14) -> 0 | E6: 8 axes: 4x NEMA ?? linear, 4x NEMA ?? rotary + drivers
B7: Mechanical | C7: =SUMIFS(BOM!$M$5:$M$6,BOM!$B$5:$B$6,$B7) -> 0 | D7: =IF($C$14=0,0,C7/$C$14) -> 0 | E7: Rails, carriages, belts, pulleys, bearings, couplings, brackets
B8: Sensors & Feedback | C8: =SUMIFS(BOM!$M$5:$M$6,BOM!$B$5:$B$6,$B8) -> 0 | D8: =IF($C$14=0,0,C8/$C$14) -> 0 | E8: Rod-angle encoders, home/limit switches
B9: PCB | C9: =SUMIFS(BOM!$M$5:$M$6,BOM!$B$5:$B$6,$B9) -> 0 | D9: =IF($C$14=0,0,C9/$C$14) -> 0 | E9: Motor-interface board fab + assembly
B10: Power | C10: =SUMIFS(BOM!$M$5:$M$6,BOM!$B$5:$B$6,$B10) -> 45.34 | D10: =IF($C$14=0,0,C10/$C$14) -> 0.12883976 | E10: Supplies, adapters, distribution
B11: Wiring & Connectors | C11: =SUMIFS(BOM!$M$5:$M$6,BOM!$B$5:$B$6,$B11) -> 0 | D11: =IF($C$14=0,0,C11/$C$14) -> 0 | E11: Cable, connectors, cable chain
B12: Safety | C12: =SUMIFS(BOM!$M$5:$M$6,BOM!$B$5:$B$6,$B12) -> 0 | D12: =IF($C$14=0,0,C12/$C$14) -> 0 | E12: E-stop, contactors, fusing, guarding
B13: Misc / Consumables | C13: =SUMIFS(BOM!$M$5:$M$6,BOM!$B$5:$B$6,$B13) -> 0 | D13: =IF($C$14=0,0,C13/$C$14) -> 0 | E13: Fasteners, printing, spares
B14: Parts subtotal (incl. tariff) | C14: =SUM(C4:C13) -> 351.91 | D14: =IF(C14=0,0,1) -> 1 | E14: Sum of all categories above
B15: Check: BOM tab TOTAL row | C15: =BOM!M7 -> 351.91 | E15: =IF(ROUND(C14-C15,2)=0,"OK - every BOM line is captured by a category","MISMATCH - a BOM row uses a category not listed above") -> OK - every BOM line is captured by a category
B17: Order-Level Charges | C17: Amount | E17: Source
B18: Shipping - DigiKey PO 101582370 | C18: 13.99 | E18: FedEx 2 Day, per order acknowledgement
B19: Sales tax - DigiKey PO 101582370 | C19: 21.99 | E19: Per order acknowledgement
B20: Order-level subtotal | C20: =SUM(C18:C19) -> 35.98
B22: TOTAL PROJECT COST TO DATE | C22: =C14+C20 -> 387.89 | E22: Parts + tariff + shipping + sales tax
B24: Budget Tracking
B25: Budget target | C25: 1500
B26: Spent to date | C26: =C22 -> 387.89
B27: Remaining | C27: =C25-C26 -> 1112.11
B28: Budget consumed | C28: =IF(C25=0,0,C26/C25) -> 0.25859333
